adv_ml/__init__.py
adv_ml/_modidx.py
adv_ml/all.py
adv_ml/backdoor.py
adv_ml/badnets.py
adv_ml/evasion.py
adv_ml/input_optimization.py
adv_ml-0.0.4.dist-info/LICENSE
adv_ml-0.0.4.dist-info/METADATA
adv_ml-0.0.4.dist-info/WHEEL
adv_ml-0.0.4.dist-info/entry_points.txt
adv_ml-0.0.4.dist-info/top_level.txt
adv_ml-0.0.4.dist-info/RECORD
